{
  "full_name": "ООО \"ВестСервисИнструмент\"",
  "trade_name": "Стоматология на Заславской-17",
  "UNP": "100166295",
  "address": {
    "full": "г. Минск, ул. Заславская, 17-1А",
    "street": "ул. Заславская",
    "building": "17-1А",
    "city": "Минск",
    "country": "Беларусь"
  },
  "phones": [
    "+375 29 311-25-68",
    "+375 29 777-25-68"
  ],
  "emails": [
    "info@zubnet.by"
  ],
  "website": "http://zubnet.by/",
  "years_in_business": 24,
  "registration_date": "2001-07-13",
  "work_hours": {
    "monday_friday": "9:00 - 20:00",
    "saturday": "По записи",
    "sunday": "Закрыто"
  },
  "metro_station": "Фрунзенская",
  "verified_sources": [
    "https://minsk.pulscen.by/firms/99560789/contacts",
    "https://2gis.by/minsk/firm/70000001042276122",
    "https://yandex.by/maps/org/stomatologicheskiy_kabinet/1105098299/"
  ],
  "services": [
    "Лечение зубов",
    "Протезирование зубов",
    "Металлокерамика",
    "Металлопластмасса",
    "Акриловое протезирование",
    "Съёмное протезирование",
    "Отбеливание зубов",
    "Профессиональная гигиена полости рта",
    "Ультразвуковая чистка",
    "Реставрация зубов",
    "Эстетическая стоматология",
    "Адгезивное протезирование",
    "Шинирование зубов",
    "Лечение пародонтоза",
    "Устранение налёта курильщика"
  ],
  "specialization": "Стоматология эконом-класса с профессиональным подходом",
  "motto": "Лечение с любовью!"
}